LICENSE
MANIFEST.in
README.md
setup.py
alloy_ml.egg-info/PKG-INFO
alloy_ml.egg-info/SOURCES.txt
alloy_ml.egg-info/dependency_links.txt
alloy_ml.egg-info/requires.txt
alloy_ml.egg-info/top_level.txt
alloyml/__init__.py
alloyml/atomic.py
alloyml/datasets.py
alloyml/plots.py
alloyml/data/Al_maxUTS_MIF.csv
alloyml/data/atomic_features.csv
alloyml/data/atomic_features_metadata.csv