Metadata-Version: 1.1
Name: alloy-ml
Version: 0.2.0.dev1
Summary: Machine learning methods for the prediction of alloy properties
Home-page: https://github.com/marioboley/alloy-ml
Author: Mario Boley
Author-email: mario.boley@gmail.com
License: MIT
Platform: UNKNOWN
Classifier: Development Status :: 3 - Alpha
Classifier: License :: OSI Approved :: MIT License
Classifier: Programming Language :: Python :: 3
